fmlpack.py
fmlpack-0.2.2.dist-info/METADATA
fmlpack-0.2.2.dist-info/WHEEL
fmlpack-0.2.2.dist-info/entry_points.txt
fmlpack-0.2.2.dist-info/top_level.txt
fmlpack-0.2.2.dist-info/RECORD
