Metadata-Version: 2.4
Name: fmlpack
Version: 0.2.2
Summary: fmlpack: A tool to convert file trees to/from TEXT, ideal for working with LLM and a lot of files (using Filesystem Markup Language -FML-).
Home-page: https://github.com/fedenunez/fmlpack
Author: fedenunez
Author-email: fedenunez+fmlpack@gmail.com
License: MIT
Classifier: Programming Language :: Python :: 3
Classifier: License :: OSI Approved :: MIT License
Classifier: Operating System :: OS Independent
Classifier: Topic :: System :: Archiving :: Packaging
Classifier: Topic :: Text Processing :: Markup
Classifier: Environment :: Console
Requires-Python: >=3.6
Requires-Dist: pathspec>=0.10.3
Dynamic: author
Dynamic: author-email
Dynamic: classifier
Dynamic: description
Dynamic: description-content-type
Dynamic: home-page
Dynamic: license
Dynamic: requires-dist
Dynamic: requires-python
Dynamic: summary
